tabulog/__init__.py
tabulog/defaults.py
tabulog/parser.py
tabulog/templates.py
tabulog-0.1.1.dist-info/LICENSE
tabulog-0.1.1.dist-info/METADATA
tabulog-0.1.1.dist-info/WHEEL
tabulog-0.1.1.dist-info/top_level.txt
tabulog-0.1.1.dist-info/RECORD
